pingsafecli/__init__.py
pingsafecli/go-rego-evaluator
pingsafecli/main.py
pingsafecli-2.3.204.data/scripts/pingsafecli
pingsafecli-2.3.204.dist-info/METADATA
pingsafecli-2.3.204.dist-info/WHEEL
pingsafecli-2.3.204.dist-info/top_level.txt
pingsafecli-2.3.204.dist-info/RECORD
