Metadata-Version: 2.1
Name: pingsafecli
Version: 2.3.204
Summary: Infrastructure as code static analysis
Home-page: https://github.com/bridgecrewio/checkov
Author: bridgecrew
Author-email: meet@bridgecrew.io
License: Apache License 2.0
Classifier: Environment :: Console
Requires-Python: >=3.7
Requires-Dist: psgraph
Provides-Extra: dev
Requires-Dist: pytest (==5.3.1) ; extra == 'dev'
Requires-Dist: coverage (==5.5) ; extra == 'dev'
Requires-Dist: coverage-badge ; extra == 'dev'
Requires-Dist: GitPython (==3.1.7) ; extra == 'dev'
Requires-Dist: bandit ; extra == 'dev'
Requires-Dist: jsonschema ; extra == 'dev'
